{"symbol": "BTC/USDT", "timestamp": 1720688402666, "datetime": "2024-07-11T09:00:02.666Z", "high": 58760.37, "low": 57083.34, "bid": 58163.81, "bidVolume": null, "ask": 58166.21, "askVolume": null, "vwap": 57848.4505727615, "open": 58732.81, "close": 58155.31, "last": 58155.31, "previousClose": null, "change": -577.5, "percentage": -0.9832664229755055, "average": 58444.06, "baseVolume": 460.97721, "quoteVolume": 26666817.3478545, "info": {"symbol": "BTCUSD", "ask": "58166.21", "bid": "58163.81", "last": "58155.31", "low": "57083.34", "high": "58760.37", "open": "58732.81", "volume": "460.97721", "volumeQuote": "26666817.3478545", "timestamp": "2024-07-11T09:00:02.666Z"}}